{"name":"attraction","label":"Attraction","workflowId":"generic","schemaDefinition":{"type":"object","allOf":[{"$ref":"#/components/schemas/AbstractContentTypeSchemaDefinition"},{"type":"object","properties":{"url":{"type":"string"},"name":{"type":"string","minLength":1},"address":{"type":"string"},"visited":{"type":"boolean"},"description":{"type":"string"},"geo_position":{"type":"object","properties":{"lat":{"type":"number","maximum":90,"minimum":-90},"lon":{"type":"number","maximum":180,"minimum":-180}},"additionalProperties":false}}}],"required":["name"],"additionalProperties":false},"metaDefinition":{"order":["name","geo_position","address","url","description","visited"],"propertiesConfig":{"url":{"label":"Url","unique":false,"helpText":"","inputType":"text"},"name":{"label":"Name","unique":true,"helpText":"","inputType":"text","isTitlePart":true},"address":{"label":"Address","unique":false,"helpText":"","inputType":"text"},"visited":{"label":"Visited","unique":false,"helpText":"","inputType":"checkbox"},"description":{"label":"Description","unique":false,"helpText":"","inputType":"richtext"},"geo_position":{"label":"Geo position","unique":false,"helpText":"","inputType":"geo"}}},"featuredImage":[]}
